nostr_bot/__init__.py
nostr_bot/bot.py
nostr_bot/cli.py
nostr_bot/examples/__init__.py
nostr_bot/examples/gotmail.py
nostr_bot/examples/mirror.py
nostr_bot/examples/ping.py
nostr_bot/examples/registration.py
nostr_bot/examples/reporting.py
nostr_bot/examples/welcome.py
nostr_bot-0.4.0.dist-info/AUTHORS.rst
nostr_bot-0.4.0.dist-info/LICENSE
nostr_bot-0.4.0.dist-info/METADATA
nostr_bot-0.4.0.dist-info/WHEEL
nostr_bot-0.4.0.dist-info/entry_points.txt
nostr_bot-0.4.0.dist-info/top_level.txt
nostr_bot-0.4.0.dist-info/RECORD
