Metadata-Version: 2.1
Name: nostr-bot
Version: 0.4.0
Summary: A Python nostr bot framework
Home-page: https://github.com/davestgermain/nostr_bot
Author: Dave St.Germain
Author-email: dave@st.germa.in
License: BSD license
Keywords: nostr_bot
Classifier: Development Status :: 2 - Pre-Alpha
Classifier: Intended Audience :: Developers
Classifier: License :: OSI Approved :: BSD License
Classifier: Natural Language :: English
Classifier: Programming Language :: Python :: 3
Classifier: Programming Language :: Python :: 3.6
Classifier: Programming Language :: Python :: 3.7
Classifier: Programming Language :: Python :: 3.8
Requires-Python: >=3.9
License-File: LICENSE
License-File: AUTHORS.rst
Requires-Dist: Click (>=7.0)
Requires-Dist: aionostr (>=0.11)
